CHANGES.rst
MANIFEST.in
README.rst
setup.py
pysimplemodel.egg-info/PKG-INFO
pysimplemodel.egg-info/SOURCES.txt
pysimplemodel.egg-info/dependency_links.txt
pysimplemodel.egg-info/top_level.txt
simple_model/__init__.py
simple_model/__version__.py
simple_model/base.py
simple_model/builder.py
simple_model/converters.py
simple_model/exceptions.py
simple_model/fields.py
simple_model/models.py
simple_model/utils.py