Metadata-Version: 1.1
Name: pysimplemodel
Version: 2.4.0
Summary: Data handling made easy
Home-page: https://github.com/lamenezes/simple-model
Author: Luiz Menezes
Author-email: luiz.menezesf@gmail.com
License: MIT
Platform: UNKNOWN
Classifier: Development Status :: 5 - Production/Stable
Classifier: Intended Audience :: Developers
Classifier: License :: OSI Approved :: MIT License
Classifier: Programming Language :: Python :: 3
Classifier: Programming Language :: Python :: 3.6
Classifier: Programming Language :: Python :: 3.7
Classifier: Topic :: Software Development :: Libraries
